[
    {
        "unique_index": 0,
        "article_index": [
            167,
            118,
            224,
            37,
            106
        ]
    },
    {
        "unique_index": 1,
        "article_index": [
            219,
            270,
            105,
            217,
            185
        ]
    },
    {
        "unique_index": 2,
        "article_index": [
            111,
            215,
            195,
            229,
            164
        ]
    },
    {
        "unique_index": 3,
        "article_index": [
            63,
            120,
            50,
            113,
            142
        ]
    },
    {
        "unique_index": 4,
        "article_index": [
            102,
            218,
            211,
            19,
            181
        ]
    },
    {
        "unique_index": 5,
        "article_index": [
            35,
            296,
            196,
            81,
            240
        ]
    },
    {
        "unique_index": 6,
        "article_index": [
            117,
            11,
            155,
            180,
            172
        ]
    },
    {
        "unique_index": 7,
        "article_index": [
            248,
            263,
            187,
            68,
            61
        ]
    },
    {
        "unique_index": 8,
        "article_index": [
            166,
            36,
            6,
            134,
            144
        ]
    },
    {
        "unique_index": 9,
        "article_index": [
            277,
            112,
            272,
            165,
            279
        ]
    },
    {
        "unique_index": 10,
        "article_index": [
            293,
            228,
            225,
            300,
            231
        ]
    },
    {
        "unique_index": 11,
        "article_index": [
            48,
            184,
            201,
            141,
            92
        ]
    },
    {
        "unique_index": 12,
        "article_index": [
            242,
            298,
            98,
            18,
            140
        ]
    },
    {
        "unique_index": 13,
        "article_index": [
            168,
            55,
            1,
            274,
            170
        ]
    },
    {
        "unique_index": 14,
        "article_index": [
            3,
            208,
            96,
            119,
            223
        ]
    },
    {
        "unique_index": 15,
        "article_index": [
            29,
            176,
            39,
            301,
            14
        ]
    },
    {
        "unique_index": 16,
        "article_index": [
            103,
            82,
            271,
            230,
            275
        ]
    },
    {
        "unique_index": 17,
        "article_index": [
            188,
            38,
            125,
            49,
            51
        ]
    },
    {
        "unique_index": 18,
        "article_index": [
            243,
            25,
            58,
            16,
            286
        ]
    },
    {
        "unique_index": 19,
        "article_index": [
            247,
            95,
            41,
            177,
            147
        ]
    },
    {
        "unique_index": 20,
        "article_index": [
            205,
            57,
            221,
            114,
            30
        ]
    },
    {
        "unique_index": 21,
        "article_index": [
            269,
            133,
            239,
            283,
            212
        ]
    },
    {
        "unique_index": 22,
        "article_index": [
            235,
            76,
            222,
            285,
            90
        ]
    },
    {
        "unique_index": 23,
        "article_index": [
            59,
            199,
            126,
            234,
            10
        ]
    },
    {
        "unique_index": 24,
        "article_index": [
            183,
            266,
            303,
            152,
            250
        ]
    },
    {
        "unique_index": 25,
        "article_index": [
            75,
            260,
            110,
            265,
            77
        ]
    },
    {
        "unique_index": 26,
        "article_index": [
            280,
            197,
            79,
            174,
            5
        ]
    },
    {
        "unique_index": 27,
        "article_index": [
            85,
            209,
            203,
            87,
            86
        ]
    },
    {
        "unique_index": 28,
        "article_index": [
            21,
            129,
            72,
            2,
            71
        ]
    },
    {
        "unique_index": 29,
        "article_index": [
            45,
            13,
            17,
            148,
            116
        ]
    },
    {
        "unique_index": 30,
        "article_index": [
            163,
            193,
            124,
            52,
            160
        ]
    },
    {
        "unique_index": 31,
        "article_index": [
            238,
            107,
            194,
            27,
            207
        ]
    },
    {
        "unique_index": 32,
        "article_index": [
            186,
            268,
            115,
            0,
            130
        ]
    },
    {
        "unique_index": 33,
        "article_index": [
            94,
            150,
            294,
            206,
            136
        ]
    },
    {
        "unique_index": 34,
        "article_index": [
            32,
            80,
            127,
            232,
            137
        ]
    },
    {
        "unique_index": 35,
        "article_index": [
            220,
            135,
            121,
            54,
            100
        ]
    },
    {
        "unique_index": 36,
        "article_index": [
            33,
            282,
            236,
            297,
            128
        ]
    },
    {
        "unique_index": 37,
        "article_index": [
            56,
            246,
            31,
            156,
            179
        ]
    },
    {
        "unique_index": 38,
        "article_index": [
            216,
            302,
            154,
            281,
            299
        ]
    },
    {
        "unique_index": 39,
        "article_index": [
            153,
            12,
            214,
            70,
            191
        ]
    },
    {
        "unique_index": 40,
        "article_index": [
            276,
            83,
            4,
            42,
            292
        ]
    },
    {
        "unique_index": 41,
        "article_index": [
            146,
            175,
            289,
            123,
            241
        ]
    },
    {
        "unique_index": 42,
        "article_index": [
            40,
            244,
            200,
            256,
            151
        ]
    },
    {
        "unique_index": 43,
        "article_index": [
            20,
            295,
            69,
            43,
            237
        ]
    },
    {
        "unique_index": 44,
        "article_index": [
            159,
            88,
            259,
            190,
            171
        ]
    },
    {
        "unique_index": 45,
        "article_index": [
            284,
            108,
            84,
            67,
            245
        ]
    },
    {
        "unique_index": 46,
        "article_index": [
            15,
            233,
            62,
            143,
            26
        ]
    },
    {
        "unique_index": 47,
        "article_index": [
            192,
            169,
            182,
            44,
            149
        ]
    },
    {
        "unique_index": 48,
        "article_index": [
            99,
            278,
            93,
            22,
            210
        ]
    },
    {
        "unique_index": 49,
        "article_index": [
            97,
            47,
            74,
            7,
            251
        ]
    },
    {
        "unique_index": 50,
        "article_index": [
            34,
            253,
            73,
            104,
            28
        ]
    },
    {
        "unique_index": 51,
        "article_index": [
            46,
            226,
            173,
            122,
            261
        ]
    },
    {
        "unique_index": 52,
        "article_index": [
            139,
            290,
            65,
            204,
            109
        ]
    },
    {
        "unique_index": 53,
        "article_index": [
            161,
            9,
            254,
            132,
            267
        ]
    },
    {
        "unique_index": 54,
        "article_index": [
            8,
            255,
            202,
            145,
            89
        ]
    },
    {
        "unique_index": 55,
        "article_index": [
            258,
            213,
            227,
            131,
            66
        ]
    },
    {
        "unique_index": 56,
        "article_index": [
            53,
            91,
            101,
            157,
            78
        ]
    },
    {
        "unique_index": 57,
        "article_index": [
            198,
            64,
            273,
            262,
            287
        ]
    },
    {
        "unique_index": 58,
        "article_index": [
            249,
            291,
            138,
            162,
            158
        ]
    },
    {
        "unique_index": 59,
        "article_index": [
            288,
            60,
            178,
            252,
            23
        ]
    },
    {
        "unique_index": 60,
        "article_index": [
            24,
            189,
            264,
            257,
            127
        ]
    },
    {
        "unique_index": 61,
        "article_index": [
            214,
            54,
            284,
            120,
            43
        ]
    },
    {
        "unique_index": 62,
        "article_index": [
            271,
            83,
            217,
            35,
            123
        ]
    },
    {
        "unique_index": 63,
        "article_index": [
            279,
            165,
            72,
            125,
            112
        ]
    },
    {
        "unique_index": 64,
        "article_index": [
            288,
            94,
            70,
            121,
            247
        ]
    },
    {
        "unique_index": 65,
        "article_index": [
            186,
            8,
            208,
            166,
            263
        ]
    },
    {
        "unique_index": 66,
        "article_index": [
            222,
            256,
            189,
            95,
            183
        ]
    },
    {
        "unique_index": 67,
        "article_index": [
            234,
            55,
            264,
            262,
            90
        ]
    },
    {
        "unique_index": 68,
        "article_index": [
            105,
            119,
            133,
            276,
            1
        ]
    },
    {
        "unique_index": 69,
        "article_index": [
            149,
            259,
            116,
            114,
            129
        ]
    },
    {
        "unique_index": 70,
        "article_index": [
            104,
            3,
            177,
            164,
            243
        ]
    },
    {
        "unique_index": 71,
        "article_index": [
            102,
            268,
            7,
            173,
            5
        ]
    },
    {
        "unique_index": 72,
        "article_index": [
            63,
            224,
            88,
            41,
            42
        ]
    },
    {
        "unique_index": 73,
        "article_index": [
            250,
            128,
            76,
            71,
            26
        ]
    },
    {
        "unique_index": 74,
        "article_index": [
            242,
            215,
            132,
            296,
            31
        ]
    },
    {
        "unique_index": 75,
        "article_index": [
            218,
            141,
            206,
            46,
            47
        ]
    },
    {
        "unique_index": 76,
        "article_index": [
            109,
            278,
            178,
            157,
            101
        ]
    },
    {
        "unique_index": 77,
        "article_index": [
            30,
            33,
            266,
            34,
            188
        ]
    },
    {
        "unique_index": 78,
        "article_index": [
            254,
            68,
            45,
            174,
            93
        ]
    },
    {
        "unique_index": 79,
        "article_index": [
            297,
            210,
            213,
            48,
            75
        ]
    },
    {
        "unique_index": 80,
        "article_index": [
            249,
            9,
            37,
            99,
            51
        ]
    },
    {
        "unique_index": 81,
        "article_index": [
            291,
            60,
            100,
            130,
            80
        ]
    },
    {
        "unique_index": 82,
        "article_index": [
            300,
            107,
            160,
            229,
            52
        ]
    },
    {
        "unique_index": 83,
        "article_index": [
            211,
            156,
            294,
            20,
            203
        ]
    },
    {
        "unique_index": 84,
        "article_index": [
            92,
            142,
            122,
            28,
            162
        ]
    },
    {
        "unique_index": 85,
        "article_index": [
            267,
            299,
            205,
            273,
            237
        ]
    },
    {
        "unique_index": 86,
        "article_index": [
            275,
            269,
            232,
            2,
            286
        ]
    },
    {
        "unique_index": 87,
        "article_index": [
            22,
            295,
            244,
            260,
            176
        ]
    },
    {
        "unique_index": 88,
        "article_index": [
            58,
            167,
            21,
            64,
            145
        ]
    },
    {
        "unique_index": 89,
        "article_index": [
            17,
            209,
            117,
            39,
            283
        ]
    },
    {
        "unique_index": 90,
        "article_index": [
            134,
            66,
            180,
            193,
            195
        ]
    },
    {
        "unique_index": 91,
        "article_index": [
            204,
            110,
            185,
            36,
            137
        ]
    },
    {
        "unique_index": 92,
        "article_index": [
            23,
            96,
            303,
            97,
            289
        ]
    },
    {
        "unique_index": 93,
        "article_index": [
            126,
            201,
            226,
            194,
            238
        ]
    },
    {
        "unique_index": 94,
        "article_index": [
            182,
            239,
            82,
            159,
            175
        ]
    },
    {
        "unique_index": 95,
        "article_index": [
            136,
            6,
            246,
            272,
            40
        ]
    },
    {
        "unique_index": 96,
        "article_index": [
            78,
            171,
            144,
            235,
            12
        ]
    },
    {
        "unique_index": 97,
        "article_index": [
            233,
            274,
            277,
            18,
            155
        ]
    },
    {
        "unique_index": 98,
        "article_index": [
            138,
            44,
            223,
            253,
            282
        ]
    },
    {
        "unique_index": 99,
        "article_index": [
            61,
            198,
            227,
            29,
            292
        ]
    },
    {
        "unique_index": 100,
        "article_index": [
            202,
            91,
            19,
            143,
            200
        ]
    },
    {
        "unique_index": 101,
        "article_index": [
            57,
            131,
            163,
            14,
            199
        ]
    },
    {
        "unique_index": 102,
        "article_index": [
            73,
            212,
            251,
            192,
            16
        ]
    },
    {
        "unique_index": 103,
        "article_index": [
            281,
            225,
            118,
            111,
            285
        ]
    },
    {
        "unique_index": 104,
        "article_index": [
            150,
            290,
            302,
            38,
            67
        ]
    },
    {
        "unique_index": 105,
        "article_index": [
            168,
            0,
            86,
            87,
            248
        ]
    },
    {
        "unique_index": 106,
        "article_index": [
            191,
            293,
            158,
            220,
            84
        ]
    },
    {
        "unique_index": 107,
        "article_index": [
            77,
            103,
            27,
            115,
            240
        ]
    },
    {
        "unique_index": 108,
        "article_index": [
            298,
            258,
            170,
            301,
            255
        ]
    },
    {
        "unique_index": 109,
        "article_index": [
            228,
            280,
            151,
            65,
            11
        ]
    },
    {
        "unique_index": 110,
        "article_index": [
            135,
            257,
            74,
            252,
            85
        ]
    },
    {
        "unique_index": 111,
        "article_index": [
            81,
            230,
            24,
            154,
            124
        ]
    },
    {
        "unique_index": 112,
        "article_index": [
            172,
            148,
            50,
            53,
            241
        ]
    },
    {
        "unique_index": 113,
        "article_index": [
            219,
            184,
            140,
            169,
            152
        ]
    },
    {
        "unique_index": 114,
        "article_index": [
            196,
            161,
            261,
            216,
            56
        ]
    },
    {
        "unique_index": 115,
        "article_index": [
            69,
            270,
            265,
            108,
            10
        ]
    },
    {
        "unique_index": 116,
        "article_index": [
            187,
            139,
            197,
            287,
            89
        ]
    },
    {
        "unique_index": 117,
        "article_index": [
            113,
            231,
            59,
            62,
            190
        ]
    },
    {
        "unique_index": 118,
        "article_index": [
            98,
            13,
            15,
            207,
            146
        ]
    },
    {
        "unique_index": 119,
        "article_index": [
            147,
            49,
            25,
            153,
            79
        ]
    },
    {
        "unique_index": 120,
        "article_index": [
            221,
            236,
            106,
            4,
            179
        ]
    },
    {
        "unique_index": 121,
        "article_index": [
            181,
            32,
            245,
            1,
            225
        ]
    },
    {
        "unique_index": 122,
        "article_index": [
            40,
            81,
            181,
            275,
            38
        ]
    },
    {
        "unique_index": 123,
        "article_index": [
            227,
            22,
            233,
            60,
            243
        ]
    },
    {
        "unique_index": 124,
        "article_index": [
            189,
            197,
            262,
            264,
            103
        ]
    },
    {
        "unique_index": 125,
        "article_index": [
            130,
            288,
            48,
            79,
            271
        ]
    },
    {
        "unique_index": 126,
        "article_index": [
            180,
            58,
            292,
            97,
            256
        ]
    },
    {
        "unique_index": 127,
        "article_index": [
            257,
            17,
            291,
            201,
            168
        ]
    },
    {
        "unique_index": 128,
        "article_index": [
            193,
            287,
            43,
            218,
            216
        ]
    },
    {
        "unique_index": 129,
        "article_index": [
            36,
            176,
            110,
            129,
            248
        ]
    },
    {
        "unique_index": 130,
        "article_index": [
            134,
            270,
            74,
            166,
            5
        ]
    },
    {
        "unique_index": 131,
        "article_index": [
            13,
            86,
            300,
            35,
            21
        ]
    },
    {
        "unique_index": 132,
        "article_index": [
            128,
            272,
            133,
            117,
            20
        ]
    },
    {
        "unique_index": 133,
        "article_index": [
            98,
            100,
            71,
            135,
            46
        ]
    },
    {
        "unique_index": 134,
        "article_index": [
            282,
            173,
            283,
            302,
            72
        ]
    },
    {
        "unique_index": 135,
        "article_index": [
            34,
            33,
            132,
            198,
            50
        ]
    },
    {
        "unique_index": 136,
        "article_index": [
            59,
            78,
            298,
            223,
            163
        ]
    },
    {
        "unique_index": 137,
        "article_index": [
            146,
            285,
            263,
            158,
            53
        ]
    },
    {
        "unique_index": 138,
        "article_index": [
            131,
            174,
            75,
            177,
            160
        ]
    },
    {
        "unique_index": 139,
        "article_index": [
            76,
            115,
            42,
            114,
            235
        ]
    },
    {
        "unique_index": 140,
        "article_index": [
            2,
            211,
            30,
            116,
            44
        ]
    },
    {
        "unique_index": 141,
        "article_index": [
            154,
            172,
            0,
            226,
            122
        ]
    },
    {
        "unique_index": 142,
        "article_index": [
            82,
            11,
            112,
            94,
            244
        ]
    },
    {
        "unique_index": 143,
        "article_index": [
            157,
            52,
            120,
            207,
            108
        ]
    },
    {
        "unique_index": 144,
        "article_index": [
            9,
            278,
            151,
            276,
            254
        ]
    },
    {
        "unique_index": 145,
        "article_index": [
            165,
            195,
            156,
            77,
            153
        ]
    },
    {
        "unique_index": 146,
        "article_index": [
            92,
            138,
            280,
            54,
            188
        ]
    },
    {
        "unique_index": 147,
        "article_index": [
            240,
            161,
            113,
            142,
            217
        ]
    },
    {
        "unique_index": 148,
        "article_index": [
            84,
            107,
            239,
            206,
            101
        ]
    },
    {
        "unique_index": 149,
        "article_index": [
            123,
            57,
            234,
            204,
            210
        ]
    },
    {
        "unique_index": 150,
        "article_index": [
            222,
            182,
            3,
            221,
            80
        ]
    },
    {
        "unique_index": 151,
        "article_index": [
            268,
            273,
            90,
            171,
            258
        ]
    },
    {
        "unique_index": 152,
        "article_index": [
            179,
            47,
            199,
            279,
            183
        ]
    },
    {
        "unique_index": 153,
        "article_index": [
            228,
            213,
            136,
            65,
            28
        ]
    },
    {
        "unique_index": 154,
        "article_index": [
            137,
            178,
            253,
            159,
            111
        ]
    },
    {
        "unique_index": 155,
        "article_index": [
            121,
            241,
            26,
            289,
            104
        ]
    },
    {
        "unique_index": 156,
        "article_index": [
            99,
            296,
            205,
            55,
            277
        ]
    },
    {
        "unique_index": 157,
        "article_index": [
            295,
            301,
            88,
            247,
            61
        ]
    },
    {
        "unique_index": 158,
        "article_index": [
            102,
            186,
            67,
            18,
            150
        ]
    },
    {
        "unique_index": 159,
        "article_index": [
            51,
            73,
            169,
            23,
            297
        ]
    },
    {
        "unique_index": 160,
        "article_index": [
            293,
            109,
            16,
            170,
            69
        ]
    },
    {
        "unique_index": 161,
        "article_index": [
            45,
            290,
            187,
            208,
            83
        ]
    },
    {
        "unique_index": 162,
        "article_index": [
            266,
            261,
            203,
            303,
            212
        ]
    },
    {
        "unique_index": 163,
        "article_index": [
            250,
            25,
            119,
            269,
            24
        ]
    },
    {
        "unique_index": 164,
        "article_index": [
            31,
            141,
            39,
            191,
            162
        ]
    },
    {
        "unique_index": 165,
        "article_index": [
            252,
            194,
            167,
            56,
            63
        ]
    },
    {
        "unique_index": 166,
        "article_index": [
            70,
            185,
            10,
            139,
            14
        ]
    },
    {
        "unique_index": 167,
        "article_index": [
            245,
            96,
            12,
            62,
            190
        ]
    },
    {
        "unique_index": 168,
        "article_index": [
            274,
            105,
            164,
            286,
            229
        ]
    },
    {
        "unique_index": 169,
        "article_index": [
            267,
            200,
            140,
            4,
            145
        ]
    },
    {
        "unique_index": 170,
        "article_index": [
            209,
            118,
            294,
            299,
            260
        ]
    },
    {
        "unique_index": 171,
        "article_index": [
            220,
            19,
            246,
            202,
            41
        ]
    },
    {
        "unique_index": 172,
        "article_index": [
            251,
            224,
            242,
            68,
            66
        ]
    },
    {
        "unique_index": 173,
        "article_index": [
            284,
            87,
            64,
            126,
            93
        ]
    },
    {
        "unique_index": 174,
        "article_index": [
            147,
            124,
            255,
            230,
            106
        ]
    },
    {
        "unique_index": 175,
        "article_index": [
            215,
            249,
            125,
            29,
            37
        ]
    },
    {
        "unique_index": 176,
        "article_index": [
            143,
            236,
            148,
            281,
            265
        ]
    },
    {
        "unique_index": 177,
        "article_index": [
            232,
            192,
            91,
            8,
            15
        ]
    },
    {
        "unique_index": 178,
        "article_index": [
            238,
            27,
            6,
            184,
            175
        ]
    },
    {
        "unique_index": 179,
        "article_index": [
            7,
            237,
            196,
            49,
            214
        ]
    },
    {
        "unique_index": 180,
        "article_index": [
            32,
            152,
            85,
            127,
            149
        ]
    },
    {
        "unique_index": 181,
        "article_index": [
            95,
            259,
            155,
            231,
            144
        ]
    },
    {
        "unique_index": 182,
        "article_index": [
            89,
            219,
            303,
            302,
            301
        ]
    }
]